{
    "info": {
        "description": "도시 소리 데이터",
        "uri": "https://www.aihub.or.kr",
        "version": 1.0,
        "year": 2021,
        "contributor": "IMR",
        "dateCreated": "2021-09-06"
    },
    "license": {
        "url": "https://www.aihub.or.kr",
        "name": "CC 0"
    },
    "audio": {
        "fileName": "4.열차_17712.wav",
        "fileSize": 621688,
        "duration": 7.048,
        "fileFormat": "wav",
        "sampleRate": "44.1kHz",
        "bitRate": "705kbps",
        "recodingType": "Mono"
    },
    "environment": {
        "recordingTime": "14:05",
        "dayNight": "주간",
        "urban": "서울특별시",
        "district": "망원동",
        "place": "빌딩사이",
        "areaUse": "상업지역",
        "weather": "맑음",
        "direction": "우",
        "distance": "15m",
        "obstacle": "없음",
        "acqMethod": "자연적",
        "acqType": "제작",
        "acqDevice": "TASCAMDR-05X",
        "micClass": "무지향성",
        "gps": {
            "latitude": 37.57,
            "longitude": 126.91
        }
    },
    "annotations": [
        {
            "labelName": "4.열차_17712_1.wav",
            "area": {
                "start": 2,
                "end": 5.048
            },
            "categories": {
                "category_01": "교통소음",
                "category_02": "열차",
                "category_03": "기차"
            },
            "subCategory": "일반열차",
            "soundQuality": "정상",
            "decibel": 75
        }
    ]
}